jetblack_lvm2/__init__.py
jetblack_lvm2/bindings.py
jetblack_lvm2/exceptions.py
jetblack_lvm2/logical_volume.py
jetblack_lvm2/lvm.py
jetblack_lvm2/physical_volume.py
jetblack_lvm2/types.py
jetblack_lvm2/utils.py
jetblack_lvm2/volume_group.py
jetblack_lvm2-0.1.0.dist-info/WHEEL
jetblack_lvm2-0.1.0.dist-info/METADATA
jetblack_lvm2-0.1.0.dist-info/RECORD
